deepfinder/__init__.py
deepfinder/deep_find.py
deepfinder/entity.py
deepfinder-1.5.0.dist-info/licenses/LICENSE
deepfinder-1.5.0.dist-info/METADATA
deepfinder-1.5.0.dist-info/WHEEL
deepfinder-1.5.0.dist-info/top_level.txt
deepfinder-1.5.0.dist-info/RECORD
