Metadata-Version: 2.4
Name: deepfinder
Version: 1.5.0
Summary: Search attributes easily using dot paths. Within structures of type dictionary, list and embedded substructures with simple format 'dict.users.0.name'.
Home-page: https://github.com/n1nj4t4nuk1/deepfinder.py
Author: Javier Parada
Author-email: javierparada@pm.me
License: MIT
Project-URL: Bug Tracker, https://github.com/n1nj4t4nuk1/deepfinder.py/issues
Keywords: find,get,dictionary,list,array,deep,find,structure,nested,nested,data
Platform: any
Classifier: Programming Language :: Python :: 3.9
Classifier: Programming Language :: Python :: 3.10
Classifier: Programming Language :: Python :: 3.11
Classifier: Programming Language :: Python :: 3.12
Classifier: Programming Language :: Python :: 3.13
Classifier: License :: OSI Approved :: MIT License
Classifier: Operating System :: OS Independent
Requires-Python: >=3.9
License-File: LICENSE
Dynamic: license-file
